comet/__init__.py
comet/comet.py
comet/models/__init__.py
comet/models/version.py
comet/util/DataCombing.py
comet/util/__init__.py
comet/util/parserIni.py
comet/util/runAndUpload.py
comet/util/weChatNotice.py
tests/__init__.py
comet.fms-0.1.2.dist-info/LICENSE
comet.fms-0.1.2.dist-info/METADATA
comet.fms-0.1.2.dist-info/WHEEL
comet.fms-0.1.2.dist-info/entry_points.txt
comet.fms-0.1.2.dist-info/top_level.txt
comet.fms-0.1.2.dist-info/zip-safe
comet.fms-0.1.2.dist-info/RECORD
