Metadata-Version: 2.1
Name: comet.fms
Version: 0.1.2
Summary: 
Home-page: https://github.com/jiqialin/comet.fms
Author: Angst
Author-email: 281491920@qq.com
License: Apache-2.0
Keywords: python httpRunner jenkins comet.fms terminal CI/CD
Platform: UNKNOWN
Classifier: Development Status :: 4 - Beta
Classifier: Intended Audience :: Developers
Classifier: License :: OSI Approved :: Apache Software License
Classifier: Programming Language :: Python
Classifier: Programming Language :: Python :: 3.6
Classifier: Programming Language :: Python :: 3.7
Classifier: Topic :: Software Development :: Libraries
Requires-Dist: requests
Requires-Dist: httprunner
Requires-Dist: pymysql
Requires-Dist: requests-toolbelt
